myLib/__init__.py
myLib/setup.py
myLib/datastructures/__init__.py
myLib/datastructures/linear/CDLL.py
myLib/datastructures/linear/CSLL.py
myLib/datastructures/linear/DLL.py
myLib/datastructures/linear/Queue.py
myLib/datastructures/linear/SLL.py
myLib/datastructures/linear/Stack.py
myLib/datastructures/linear/__init__.py
myLib/datastructures/nodes/DNode.py
myLib/datastructures/nodes/TNode.py
myLib/datastructures/nodes/__init__.py
myLib/datastructures/trees/AVL.py
myLib/datastructures/trees/BST.py
myLib/datastructures/trees/__init__.py
ENSF_338_Final_Project_Package-1.0.dist-info/METADATA
ENSF_338_Final_Project_Package-1.0.dist-info/WHEEL
ENSF_338_Final_Project_Package-1.0.dist-info/top_level.txt
ENSF_338_Final_Project_Package-1.0.dist-info/RECORD
