Metadata-Version: 2.1
Name: ENSF-338-Final-Project-Package
Version: 1.0
Summary: different types of datastructures
Author: Zachariah Blair
Author-email: zachariah.blair@gmail.com
